{
  "DevicesConfiguration": {
    "Devices": [
      {
        "Name": "GPON OLT A",
        "IpAddress": "10.1.1.21",
        "SnmpPort": "161",
        "SnmpVersion": "2",
        "SnmpCommunity": "public",
        "SnmpTimeout": 6000,
        "IpHostWebManagementPort": 80
      },
      {
        "Name": "GPON OLT B",
        "IpAddress": "10.1.1.11",
        "SnmpPort": "161",
        "SnmpVersion": "2",
        "SnmpCommunity": "public",
        "SnmpTimeout": 6000,
        "IpHostWebManagementPort": 80
      },
      {
        "Name": "GPON OLT C",
        "IpAddress": "10.2.1.11",
        "SnmpPort": "161",
        "SnmpVersion": "2",
        "SnmpCommunity": "public",
        "SnmpTimeout": 6000,
        "IpHostWebManagementPort": 80
      }
    ]
  }
} 
